pye3d/observation.py
pye3d/refraction.py
pye3d/__init__.py
pye3d/constants.py
pye3d/camera.py
pye3d/kalman.py
pye3d/detector_3d.py
pye3d/geometry/intersections.py
pye3d/geometry/projections.py
pye3d/geometry/utilities.py
pye3d/geometry/__init__.py
pye3d/geometry/primitives.py
pye3d/cpp/pupil_detection_3d.cpython-37m-x86_64-linux-gnu.so
pye3d/cpp/__init__.py
pye3d/cpp/refraction_correction.cpython-37m-x86_64-linux-gnu.so
pye3d/cpp/projections.cpython-37m-x86_64-linux-gnu.so
pye3d/eye_model/base.py
pye3d/eye_model/background_helper.py
pye3d/eye_model/__init__.py
pye3d/eye_model/abstract.py
pye3d/eye_model/asynchronous.py
pye3d/refraction_models/default_refraction_model_sphere_center_degree_3.msgpack
pye3d/refraction_models/default_refraction_model_pupil_circle_degree_3.msgpack
pye3d/refraction_models/default_refraction_model_gaze_vector_degree_3.msgpack
pye3d/refraction_models/default_refraction_model_radius_degree_3.msgpack
pye3d-0.3.2.dist-info/METADATA
pye3d-0.3.2.dist-info/WHEEL
pye3d-0.3.2.dist-info/RECORD
pye3d-0.3.2.dist-info/top_level.txt
pye3d-0.3.2.dist-info/LICENSE
