Metadata-Version: 2.1
Name: pye3d
Version: 0.3.2
Summary: 3D eye model
Home-page: https://github.com/pupil-labs/pye3d-detector
Author: Pupil Labs GmbH
Author-email: info@pupil-labs.com
License: UNKNOWN
Platform: UNKNOWN
Classifier: Development Status :: 5 - Production/Stable
Classifier: License :: OSI Approved :: MIT License
Classifier: License :: Other/Proprietary License
Classifier: Natural Language :: English
Classifier: Operating System :: MacOS
Classifier: Operating System :: Microsoft :: Windows
Classifier: Operating System :: POSIX :: Linux
Classifier: Programming Language :: Python :: 3
Classifier: Programming Language :: Python :: 3 :: Only
Classifier: Topic :: Scientific/Engineering
Requires-Python: >=3.6
License-File: LICENSE
Requires-Dist: msgpack (>=1.0)
Requires-Dist: numpy
Requires-Dist: sortedcontainers
Requires-Dist: importlib-metadata ; python_version < "3.8"
Provides-Extra: docs
Requires-Dist: furo ; extra == 'docs'
Requires-Dist: jaraco.packaging (>=8.2) ; extra == 'docs'
Requires-Dist: rst.linker (>=1.9) ; extra == 'docs'
Requires-Dist: sphinx (<4.4) ; extra == 'docs'
Provides-Extra: examples
Requires-Dist: opencv-python ; extra == 'examples'
Requires-Dist: pupil-detectors ; extra == 'examples'
Provides-Extra: legacy_sklearn_models
Requires-Dist: joblib ; extra == 'legacy_sklearn_models'
Requires-Dist: scikit-learn ; extra == 'legacy_sklearn_models'
Provides-Extra: testing
Requires-Dist: matplotlib ; extra == 'testing'
Requires-Dist: opencv-python-headless (==4.6.0.66) ; extra == 'testing'
Requires-Dist: pandas ; extra == 'testing'
Requires-Dist: pytest (>=6) ; extra == 'testing'
Requires-Dist: pytest-checkdocs (>=2.4) ; extra == 'testing'
Requires-Dist: pytest-cov ; extra == 'testing'
Requires-Dist: pytest-enabler (>=1.0.1) ; extra == 'testing'
Requires-Dist: scikit-image ; extra == 'testing'
Provides-Extra: with_opencv
Requires-Dist: opencv-python ; extra == 'with_opencv'
